deps/pdfminer.six-20200517.dev1-py3-none-any.whl
deps/pdfplumber-0.5.21.dev1-py3-none-any.whl
libpdf/__init__.py
libpdf/_import_forks.py
libpdf/apiobjects.py
libpdf/catalog.py
libpdf/core.py
libpdf/exceptions.py
libpdf/extract.py
libpdf/log.py
libpdf/models/__init__.py
libpdf/models/chapter.py
libpdf/models/coord.py
libpdf/models/element.py
libpdf/models/figure.py
libpdf/models/file.py
libpdf/models/file_meta.py
libpdf/models/horizontal_box.py
libpdf/models/link.py
libpdf/models/model_base.py
libpdf/models/page.py
libpdf/models/paragraph.py
libpdf/models/position.py
libpdf/models/rect.py
libpdf/models/root.py
libpdf/models/table.py
libpdf/parameters.py
libpdf/process.py
libpdf/progress.py
libpdf/tables.py
libpdf/textbox.py
libpdf/utils.py
libpdf-0.1.0.dist-info/LICENSE
libpdf-0.1.0.dist-info/METADATA
libpdf-0.1.0.dist-info/WHEEL
libpdf-0.1.0.dist-info/entry_points.txt
libpdf-0.1.0.dist-info/RECORD
