Metadata-Version: 2.1
Name: libpdf
Version: 0.1.0
Summary: Extract structured data from PDFs.
Home-page: http://pypi.python.org/pypi/libpdf
License: MIT
Author: Marco Heinemann
Author-email: marco.heinemann@useblocks.com
Maintainer: Jui-Wen Chen
Maintainer-email: jui-wen.chen@useblocks.com
Requires-Python: >=3.8,<4.0
Classifier: Development Status :: 3 - Alpha
Classifier: Intended Audience :: Developers
Classifier: License :: OSI Approved :: MIT License
Classifier: Operating System :: OS Independent
Classifier: Programming Language :: Python
Classifier: Programming Language :: Python :: 3
Classifier: Programming Language :: Python :: 3.8
Classifier: Programming Language :: Python :: 3.9
Classifier: Programming Language :: Python :: 3.10
Classifier: Programming Language :: Python :: 3.11
Classifier: Programming Language :: Python :: 3.12
Classifier: Topic :: Scientific/Engineering
Classifier: Topic :: Scientific/Engineering :: Information Analysis
Classifier: Topic :: Software Development
Classifier: Topic :: Software Development :: Libraries
Classifier: Topic :: Software Development :: Libraries :: Python Modules
Classifier: Topic :: Text Processing
Classifier: Topic :: Utilities
Provides-Extra: colorama
Provides-Extra: docs
Provides-Extra: tqdm
Requires-Dist: PyYAML (>=6,<7)
Requires-Dist: chardet (>=4,<5)
Requires-Dist: click (>=8,<9)
Requires-Dist: colorama (>=0.4.4,<0.5.0) ; extra == "colorama"
Requires-Dist: pillow (>=9.0.1,<9.1.0)
Requires-Dist: pycryptodome (>=3.9.9,<4.0.0)
Requires-Dist: ruamel.yaml (>=0.17,<0.18)
Requires-Dist: sortedcontainers (>=2.3.0,<3.0.0)
Requires-Dist: sphinx ; extra == "docs"
Requires-Dist: sphinx_rtd_theme ; extra == "docs"
Requires-Dist: sphinxcontrib-plantuml ; extra == "docs"
Requires-Dist: tqdm (>=4.50.0,<5.0.0) ; extra == "tqdm"
Requires-Dist: unicodecsv (>=0.14.1,<0.15.0)
Requires-Dist: wand (>=0.6.5,<0.7.0)
Project-URL: Documentation, http://libpdf.readthedocs.io/en/latest
Project-URL: Repository, http://github.com/useblocks/libpdf
